datasette_short_links/__init__.py
datasette_short_links/static/index.js
datasette_short_links/templates/datasette-short-links-admin.html
datasette_short_links-0.0.1a5.dist-info/LICENSE
datasette_short_links-0.0.1a5.dist-info/METADATA
datasette_short_links-0.0.1a5.dist-info/WHEEL
datasette_short_links-0.0.1a5.dist-info/entry_points.txt
datasette_short_links-0.0.1a5.dist-info/top_level.txt
datasette_short_links-0.0.1a5.dist-info/RECORD
