Metadata-Version: 2.1
Name: datasette-short-links
Version: 0.0.1a5
Author: Alex Garcia
License: Apache-2.0
Project-URL: Homepage, https://github.com/datasette/datasette-short-links
Project-URL: Changelog, https://github.com/datasette/datasette-short-links/releases
Project-URL: Issues, https://github.com/datasette/datasette-short-links/issues
Project-URL: CI, https://github.com/datasette/datasette-short-links/actions
Classifier: License :: OSI Approved :: Apache Software License
License-File: LICENSE
Requires-Dist: datasette >=1.0a6
Requires-Dist: python-ulid
Provides-Extra: test
Requires-Dist: pytest ; extra == 'test'
Requires-Dist: pytest-asyncio ; extra == 'test'
